pySecDec/__init__.py
pySecDec/algebra.py
pySecDec/disteval.py
pySecDec/disteval_benchmark.py
pySecDec/expansion.py
pySecDec/formset.py
pySecDec/generating_vectors.py
pySecDec/integral_interface.py
pySecDec/make_package.py
pySecDec/make_regions.py
pySecDec/matrix_sort.py
pySecDec/metadata.py
pySecDec/misc.py
pySecDec/polytope.py
pySecDec/subtraction.py
pySecDec/test_algebra.py
pySecDec/test_expansion.py
pySecDec/test_integral_interface.py
pySecDec/test_make_regions.py
pySecDec/test_matrix_sort.py
pySecDec/test_misc.py
pySecDec/test_polytope.py
pySecDec/test_subtraction.py
pySecDec/loop_integral/__init__.py
pySecDec/loop_integral/common.py
pySecDec/loop_integral/draw.py
pySecDec/loop_integral/from_graph.py
pySecDec/loop_integral/from_propagators.py
pySecDec/loop_integral/leading_order.py
pySecDec/loop_integral/loop_package.py
pySecDec/loop_integral/loop_regions.py
pySecDec/loop_integral/test_draw.py
pySecDec/loop_integral/test_leading_order.py
pySecDec/loop_integral/test_loop_integral.py
pySecDec/decomposition/__init__.py
pySecDec/decomposition/common.py
pySecDec/decomposition/geometric.py
pySecDec/decomposition/iterative.py
pySecDec/decomposition/splitting.py
pySecDec/decomposition/test_common.py
pySecDec/decomposition/test_geometric_decomposition.py
pySecDec/decomposition/test_iterative_decomposition.py
pySecDec/decomposition/test_splitting.py
pySecDec/code_writer/__init__.py
pySecDec/code_writer/make_package.py
pySecDec/code_writer/sum_package.py
pySecDec/code_writer/template_parser.py
pySecDec/code_writer/test_make_package.py
pySecDec/code_writer/test_sum_package.py
pySecDec/code_writer/test_template_parser.py
pySecDec/code_writer/templates/sum_package/Makefile
pySecDec/code_writer/templates/sum_package/Makefile.conf
pySecDec/code_writer/templates/sum_package/README
pySecDec/code_writer/templates/sum_package/integrate_name.cpp
pySecDec/code_writer/templates/sum_package/name.hpp
pySecDec/code_writer/templates/sum_package/src/amplitude.cpp
pySecDec-1.6.5.post1.dist-info/METADATA
pySecDec-1.6.5.post1.dist-info/WHEEL
pySecDec-1.6.5.post1.dist-info/entry_points.txt
pySecDec-1.6.5.post1.dist-info/RECORD