Metadata-Version: 2.1
Name: pySecDec
Version: 1.6.5.post1
Summary: Numerical evaluator of integrals implementing the "Sector Decomposition" method (arXiv:2305.19768, arXiv:2108.10807, arXiv:1703.09692, arXiv:hep-ph/0004013, arXiv:0803.4177).
Requires-Python: >=3.8
License: GPLv3
Author: Sophia Borowka, Bakar Chargeishvili, Gudrun Heinrich, Stephan Jahn, Stephen Jones, Matthias Kerner, Florian Langer, Vitaly Magerya, Anton Olsson, Andres Poldaru, Johannes Schlenk, Emilio Villa, Tom Zirke
Classifier: Development Status :: 5 - Production/Stable
Classifier: Environment :: Console
Classifier: Environment :: GPU :: NVIDIA CUDA
Classifier: Intended Audience :: Science/Research
Classifier: Natural Language :: English
Classifier: Operating System :: Unix
Classifier: Programming Language :: C++
Classifier: Programming Language :: Python :: 3
Classifier: Topic :: Scientific/Engineering :: Physics
Home-Page: https://github.com/gudrunhe/secdec
Provides-Extra: testing
Requires-Dist: pytest; extra == 'testing'
Requires-Dist: pytest-timeout; extra == 'testing'
Requires-Dist: pytest-cov; extra == 'testing'
Provides-Extra: documentation
Requires-Dist: sphinx>=1.6.3; extra == 'documentation'
Requires-Dist: numpy<3,>=1.23
Requires-Dist: sympy!=1.11.*,!=1.12.*,<2,>=1.10.1
Requires-Dist: nest-asyncio~=1.5
